agno_yaml/__init__.py
agno_yaml/agno_providers.py
agno_yaml/agno_utils.py
agno_yaml/main.py
agno_yaml/yaml_loader.py
agno_yaml_builder-0.1.3.dist-info/licenses/LICENSE
agno_yaml_builder-0.1.3.dist-info/METADATA
agno_yaml_builder-0.1.3.dist-info/WHEEL
agno_yaml_builder-0.1.3.dist-info/entry_points.txt
agno_yaml_builder-0.1.3.dist-info/top_level.txt
agno_yaml_builder-0.1.3.dist-info/RECORD
