Metadata-Version: 2.4
Name: agno-yaml-builder
Version: 0.1.3
Summary: A Python utility library for defining and constructing Agno Agents, Teams, and Workflows using declarative YAML configuration files
License-Expression: Apache-2.0
Project-URL: Homepage, https://github.com/zilin/agno-yaml
Requires-Python: >=3.12
License-File: LICENSE
Requires-Dist: agno>=1.2.6
Requires-Dist: duckduckgo-search>=7.5.5
Requires-Dist: fastapi>=0.115.12
Requires-Dist: google-genai>=1.8.0
Requires-Dist: lxml-html-clean>=0.4.1
Requires-Dist: newspaper4k>=0.9.3.1
Requires-Dist: pyyaml>=6.0.2
Requires-Dist: uvicorn>=0.34.0
Requires-Dist: yfinance>=0.2.55
Dynamic: license-file
